tmma/__init__.py
tmma/_h5utils.py
tmma/_plot.py
tmma/_utils.py
tmma/tmm.py
tmma/database/AllRoundRobinMaterials.pdf
tmma/database/__init__.py
tmma/database/path.py
tmma/database/_csv/mat_MDF12mm_plane_00deg.csv
tmma/database/_csv/mat_MDF12mm_structured_30deg.csv
tmma/database/_csv/mat_MDF12mm_structured_45deg.csv
tmma/database/_csv/mat_MDF12mm_structured_45degIn32degOut.csv
tmma/database/_csv/mat_MDF12mm_structured_60deg.csv
tmma/database/_csv/mat_MDF25mmA_plane_00deg.csv
tmma/database/_csv/mat_MDF25mmB_plane_00deg.csv
tmma/database/_csv/mat_RockFonSonarG_00deg.csv
tmma/database/_csv/mat_RockFonSonarG_30deg.csv
tmma/database/_csv/mat_RockFonSonarG_45deg.csv
tmma/database/_csv/mat_RockFonSonarG_45degIn32degOut.csv
tmma/database/_csv/mat_RockFonSonarG_60deg.csv
tmma/database/_csv/mat_Tiles.csv
tmma/database/_csv/mat_scene08_absorber.csv
tmma/database/_csv/mat_scene08_concrete.csv
tmma/database/_csv/mat_scene08_paintedConcrete.csv
tmma/database/_csv/mat_scene08_tablesEquipment.csv
tmma/database/_csv/mat_scene09_ceiling.csv
tmma/database/_csv/mat_scene09_concrete.csv
tmma/database/_csv/mat_scene09_floor.csv
tmma/database/_csv/mat_scene09_plaster.csv
tmma/database/_csv/mat_scene09_windows.csv
tmma/database/_csv/mat_scene10_ceiling.csv
tmma/database/_csv/mat_scene10_floor.csv
tmma/database/_csv/mat_scene10_plaster.csv
tmma/database/_csv/mat_scene10_seating.csv
tmma/database/_csv/mat_scene10_stagePanels.csv
tmma/database/_csv/mat_scene10_structuredPlaster.csv
tmma/database/_csv/mat_scene11_brickwall.csv
tmma/database/_csv/mat_scene11_concrete.csv
tmma/database/_csv/mat_scene11_linoleum.csv
tmma/database/_csv/mat_scene11_parquet.csv
tmma/database/_csv/mat_scene11_seating.csv
tmma/database/_csv/mat_scene11_whitePanels.csv
tmma/database/_csv/mat_scene11_woodPanels.csv
tmma/database/_descr/mat_MDF12mm_plane.txt
tmma/database/_descr/mat_MDF12mm_plane_structured.txt
tmma/database/_descr/mat_MDF25mmA_plane.txt
tmma/database/_descr/mat_MDF25mmB_plane.txt
tmma-0.0.3.0.dist-info/LICENSE
tmma-0.0.3.0.dist-info/METADATA
tmma-0.0.3.0.dist-info/WHEEL
tmma-0.0.3.0.dist-info/top_level.txt
tmma-0.0.3.0.dist-info/RECORD
