Metadata-Version: 2.1
Name: tmma
Version: 0.0.3.0
Summary: Transfer Matrix Models for modeling acoustic treatments
Home-page: https://github.com/jvcarli/tmma
Author: Rinaldi Polese Petrolli
Author-email: rinaldipp@gmail.com
Classifier: Programming Language :: Python :: 3
Classifier: License :: OSI Approved :: MIT License
Classifier: Operating System :: OS Independent
Requires-Python: >=3.6
License-File: LICENSE
Requires-Dist: numpy
Requires-Dist: scipy
Requires-Dist: matplotlib
Requires-Dist: pandas
Requires-Dist: mpmath
Requires-Dist: xlsxwriter
Requires-Dist: h5py
